Metadata-Version: 1.0
Name: consistent_hash
Version: 1.0
Summary: Implements consistent hashing with Python and the algorithm is the same as libketama.
Home-page: https://github.com/yummybian
Author: Yummy Bian
Author-email: yummy.bian#gmail.com
License: BSD
Keywords: consistent hash hashing
Platform: Any
Classifier: Development Status :: 4 - Beta
Classifier: Intended Audience :: Developers
Classifier: License :: OSI Approved :: BSD License
Classifier: Operating System :: OS Independent
Classifier: Programming Language :: Python
Classifier: Topic :: Software Development :: Libraries :: Python Modules
